ai_pipeline_params/__init__.py
ai_pipeline_params-0.0.3.dist-info/LICENSE
ai_pipeline_params-0.0.3.dist-info/METADATA
ai_pipeline_params-0.0.3.dist-info/WHEEL
ai_pipeline_params-0.0.3.dist-info/top_level.txt
ai_pipeline_params-0.0.3.dist-info/RECORD
