Metadata-Version: 2.1
Name: ai-pipeline-params
Version: 0.0.3
Summary: Functions to set and use the AI Pipeline Params
Home-page: https://github.ibm.com/OpenAIHub/openaihub-pipeline-samples/tree/master/wml-containers
Author: Adrian Zhuang
Author-email: wzhuang@us.ibm.com
License: UNKNOWN
Platform: UNKNOWN
Classifier: Programming Language :: Python :: 3
Classifier: License :: OSI Approved :: MIT License
Classifier: Operating System :: OS Independent
Requires-Dist: kfp
Requires-Dist: kubernetes
